yafowil.widget.cron-1.3-py3.9-nspkg.pth
yafowil/widget/cron/__init__.py
yafowil/widget/cron/example.py
yafowil/widget/cron/tests.py
yafowil/widget/cron/widget.py
yafowil/widget/cron/locales/yafowil.widget.cron.pot
yafowil/widget/cron/locales/de/LC_MESSAGES/yafowil.widget.cron.mo
yafowil/widget/cron/locales/de/LC_MESSAGES/yafowil.widget.cron.po
yafowil/widget/cron/locales/en/LC_MESSAGES/yafowil.widget.cron.mo
yafowil/widget/cron/locales/en/LC_MESSAGES/yafowil.widget.cron.po
yafowil/widget/cron/resources/widget.css
yafowil/widget/cron/resources/widget.js
yafowil/widget/cron/resources/widget.less
yafowil_widget_cron-1.3.dist-info/licenses/LICENSE.rst
yafowil_widget_cron-1.3.dist-info/METADATA
yafowil_widget_cron-1.3.dist-info/WHEEL
yafowil_widget_cron-1.3.dist-info/entry_points.txt
yafowil_widget_cron-1.3.dist-info/namespace_packages.txt
yafowil_widget_cron-1.3.dist-info/top_level.txt
yafowil_widget_cron-1.3.dist-info/RECORD
